{
    "created_time": "2021-03-02T09:54:17Z",
    "files": [
        {
            "attachment_folder": "",
            "created_time": "2021-03-02T09:54:17Z",
            "id": "0",
            "modified_time": "2021-03-02T09:54:17Z",
            "name": "404.md",
            "tags": [
            ]
        },
        {
            "attachment_folder": "",
            "created_time": "2021-03-02T09:54:17Z",
            "id": "0",
            "modified_time": "2021-03-02T09:54:17Z",
            "name": "about.md",
            "tags": [
            ]
        },
        {
            "attachment_folder": "",
            "created_time": "2021-03-02T09:54:17Z",
            "id": "0",
            "modified_time": "2021-03-02T09:54:17Z",
            "name": "archives.md",
            "tags": [
            ]
        },
        {
            "attachment_folder": "",
            "created_time": "2021-03-02T09:54:17Z",
            "id": "0",
            "modified_time": "2021-03-02T09:54:17Z",
            "name": "categories.md",
            "tags": [
            ]
        },
        {
            "attachment_folder": "",
            "created_time": "2021-03-02T09:54:17Z",
            "id": "0",
            "modified_time": "2021-03-02T09:54:17Z",
            "name": "links.md",
            "tags": [
            ]
        },
        {
            "attachment_folder": "",
            "created_time": "2021-03-02T09:54:17Z",
            "id": "0",
            "modified_time": "2021-03-02T09:54:17Z",
            "name": "open-source.md",
            "tags": [
            ]
        },
        {
            "attachment_folder": "",
            "created_time": "2021-03-02T09:54:17Z",
            "id": "0",
            "modified_time": "2021-03-02T09:54:17Z",
            "name": "wiki.md",
            "tags": [
            ]
        }
    ],
    "folders": [
    ],
    "id": "0",
    "modified_time": "2021-03-02T09:54:17Z",
    "version": "1"
}
